NASADEM/NASADEM.py
NASADEM/__init__.py
NASADEM/version.py
nasadem-2.0.1.dist-info/licenses/LICENSE
nasadem-2.0.1.dist-info/METADATA
nasadem-2.0.1.dist-info/WHEEL
nasadem-2.0.1.dist-info/top_level.txt
nasadem-2.0.1.dist-info/RECORD
