Metadata-Version: 2.4
Name: NASADEM
Version: 2.0.1
Summary: Shuttle Radar Topography Mission (SRTM) Digital Elevation Model (DEM) search and download utility
Author-email: "Gregory H. Halverson" <gregory.h.halverson@jpl.nasa.gov>
Project-URL: Homepage, https://github.com/JPL-Evapotranspiration-Algorithms/NASADEM
Classifier: Programming Language :: Python :: 3
Classifier: Operating System :: OS Independent
Requires-Python: >=3.10
License-File: LICENSE
Requires-Dist: colored-logging
Requires-Dist: earthaccess>=0.8.0
Requires-Dist: ECOv002_calval_tables
Requires-Dist: numpy
Requires-Dist: rasters>=1.14.0
Requires-Dist: sentinel-tiles
Requires-Dist: shapely
Provides-Extra: dev
Requires-Dist: build; extra == "dev"
Requires-Dist: pytest>=6.0; extra == "dev"
Requires-Dist: pytest-cov; extra == "dev"
Requires-Dist: jupyter; extra == "dev"
Requires-Dist: pytest; extra == "dev"
Requires-Dist: tox; extra == "dev"
Requires-Dist: twine; extra == "dev"
Dynamic: license-file
